dify_easy-0.1.0.dist-info/METADATA
dify_easy-0.1.0.dist-info/WHEEL
dify_easy-0.1.0.dist-info/entry_points.txt
dify_easy-0.1.0.dist-info/licenses/LICENSE
dify_easy/__init__.py
dify_easy/__version__.py
dify_easy/app.py
dify_easy/dify-plugin-pdm-template-provider.template
dify_easy/dify-plugin-pdm-template-tool.template
dify_easy/model.py
dify_easy-0.1.0.dist-info/RECORD
