Metadata-Version: 2.1
Name: dify-easy
Version: 0.1.0
Summary: Default template for PDM package
Author-Email: jingfelix <jingfelix@outlook.com>
License: MIT
Requires-Python: >=3.12
Requires-Dist: pydantic>=2.11.5
Requires-Dist: pyyaml>=6.0.2
Requires-Dist: structlog>=25.4.0
Requires-Dist: typer>=0.16.0
